inspire_query_parser/__init__.py
inspire_query_parser/ast.py
inspire_query_parser/config.py
inspire_query_parser/parser.py
inspire_query_parser/parsing_driver.py
inspire_query_parser/stateful_pypeg_parser.py
inspire_query_parser/utils/__init__.py
inspire_query_parser/utils/format_parse_tree.py
inspire_query_parser/utils/visitor_utils.py
inspire_query_parser/visitors/__init__.py
inspire_query_parser/visitors/elastic_search_visitor.py
inspire_query_parser/visitors/restructuring_visitor.py
inspire_query_parser/visitors/visitor_impl.py
inspire_query_parser-6.0.61.dist-info/licenses/LICENSE
inspire_query_parser-6.0.61.dist-info/METADATA
inspire_query_parser-6.0.61.dist-info/WHEEL
inspire_query_parser-6.0.61.dist-info/top_level.txt
inspire_query_parser-6.0.61.dist-info/RECORD
