Metadata-Version: 2.4
Name: inspire-query-parser
Version: 6.0.61
Summary: A PEG-based query parser for INSPIRE.
Home-page: https://github.com/inspirehep/inspire-query-parser
Author: CERN
Author-email: admin@inspirehep.net
License: GPLv3
Platform: any
Classifier: Development Status :: 4 - Beta
Classifier: Environment :: Web Environment
Classifier: Intended Audience :: Developers
Classifier: License :: OSI Approved :: GNU General Public License v3 (GPLv3)
Classifier: Operating System :: OS Independent
Classifier: Programming Language :: Python
Classifier: Programming Language :: Python :: 3.11
Classifier: Topic :: Internet :: WWW/HTTP :: Dynamic Content
Classifier: Topic :: Software Development :: Libraries :: Python Modules
License-File: LICENSE
Requires-Dist: inspire-schemas~=61.0
Requires-Dist: inspire-utils>=3.0.0,~=3.0
Requires-Dist: pypeg2>=2.15.2
Requires-Dist: python-dateutil>=2.6.1
Requires-Dist: six>=1.11.0
Requires-Dist: datefinder>=0.7.1
Provides-Extra: docs
Provides-Extra: tests
Requires-Dist: flake8>=3.5.0; extra == "tests"
Requires-Dist: mock>=2.0.0; extra == "tests"
Requires-Dist: pytest-cov>=2.6.0; extra == "tests"
Requires-Dist: pytest>=6.2.5; extra == "tests"
Provides-Extra: dev
Requires-Dist: pre-commit>=4.2.0; extra == "dev"
Provides-Extra: all
Requires-Dist: flake8>=3.5.0; extra == "all"
Requires-Dist: mock>=2.0.0; extra == "all"
Requires-Dist: pytest-cov>=2.6.0; extra == "all"
Requires-Dist: pytest>=6.2.5; extra == "all"
Requires-Dist: pre-commit>=4.2.0; extra == "all"
Requires-Dist: flake8>=3.5.0; extra == "all"
Requires-Dist: mock>=2.0.0; extra == "all"
Requires-Dist: pytest-cov>=2.6.0; extra == "all"
Requires-Dist: pytest>=6.2.5; extra == "all"
Requires-Dist: pre-commit>=4.2.0; extra == "all"
Dynamic: author
Dynamic: author-email
Dynamic: classifier
Dynamic: description
Dynamic: description-content-type
Dynamic: home-page
Dynamic: license
Dynamic: license-file
Dynamic: platform
Dynamic: provides-extra
Dynamic: requires-dist
Dynamic: summary
